LICENSE
MANIFEST.in
README
setup.py
seinfeld/__init__.py
seinfeld/seinfeld.py
seinfeld.egg-info/PKG-INFO
seinfeld.egg-info/SOURCES.txt
seinfeld.egg-info/dependency_links.txt
seinfeld.egg-info/requires.txt
seinfeld.egg-info/top_level.txt